flowty/__init__.py
flowty/__main__.py
flowty/flowty.pyd
flowty-2.1.0.dist-info/LICENSE
flowty-2.1.0.dist-info/METADATA
flowty-2.1.0.dist-info/WHEEL
flowty-2.1.0.dist-info/entry_points.txt
flowty-2.1.0.dist-info/top_level.txt
flowty-2.1.0.dist-info/RECORD
