Metadata-Version: 2.1
Name: flowty
Version: 2.1.0
Summary: Flowty Network Optimization Solver
Author-email: Flowty <info@flowty.ai>
License: Community License
Project-URL: Homepage, https://flowty.ai
Project-URL: Documentation, https://docs.flowty.ai
Project-URL: Bug Tracker, https://github.com/flowty/flowty/issues
Keywords: Optimization,Nework Optimization,Combinatorial Optimization,Linear Programming,Integer Programming,Operations Research,Mathematical Programming
Classifier: License :: Other/Proprietary License
Classifier: Programming Language :: Python :: 3.9
Classifier: Programming Language :: Python :: 3.10
Classifier: Programming Language :: Python :: 3.11
Classifier: Programming Language :: Python :: 3.12
Requires-Python: >=3.9
License-File: LICENSE
